{"inkVersion":21,"root":[["^Syviis: Hey Lyra! I got the goods! Let's goooo!","\n","ev","str","^Continue","/str","/ev",{"*":"0.c-0","flg":20},{"c-0":["^ ",{"->":"noresponse"},"\n",{"->":"0.g-0"},{"#f":5}],"g-0":["done",{"#f":5}]}],"done",{"noresponse":[["^... No response...","\n","ev","str","^Continue","/str","/ev",{"*":".^.c-0","flg":20},{"c-0":["^ ",{"->":"syviisfirst"},"\n",{"#f":5}]}],{"#f":1}],"syviisfirst":[["^Syviis: Oh Lyraaa why are you hidinggggggg?","\n","ev","str","^Continue","/str","/ev",{"*":".^.c-0","flg":20},{"c-0":["^ ",{"->":"syviissecond"},"\n",{"#f":5}]}],{"#f":1}],"syviissecond":[["^... No response ... again ...","\n","ev","str","^Continue","/str","/ev",{"*":".^.c-0","flg":20},{"c-0":["^ ",{"->":"syviisthird"},"\n",{"#f":5}]}],{"#f":1}],"syviisthird":[["^Syviis: I swear on the Mother if you-","\n","^<i>you hear a slight rustle in the leaves</i>","\n","ev","str","^Continue","/str","/ev",{"*":".^.c-0","flg":20},{"c-0":["^ ",{"->":"dialogue"},"\n",{"#f":5}]}],{"#f":1}],"dialogue":[["^Lyra: AHH WAAA NO HI HI I'M HERE","\n","^<i> you shake at the sudden eruption of Lyra's loud presence</i>","\n","ev","str","^Continue","/str","/ev",{"*":".^.c-0","flg":20},{"c-0":["^ ",{"->":"dialogue1"},"\n",{"#f":5}]}],{"#f":1}],"dialogue1":[["^Syviis: Ow volume much? C'mon, isn't the forest supposed to be a sacred place?","\n","^<i> Lyra rolls her eyes at you </i>","\n","ev","str","^Continue","/str","/ev",{"*":".^.c-0","flg":20},{"c-0":["^ ",{"->":"dialogue2"},"\n",{"#f":5}]}],{"#f":1}],"dialogue2":[["^Lyra: Yes of course duh, but the mother wouldn't want us to not have a little fun, right?","\n","ev","str","^Continue","/str","/ev",{"*":".^.c-0","flg":20},{"c-0":["^ ",{"->":"dialogue3"},"\n",{"#f":5}]}],{"#f":1}],"dialogue3":[["^Syviis: <i> you pat her head</i> Okay whatever you and the Mother say. Let's get some good ol' shroomies.","\n","^<i> you playfully drap your arm over her shoulders</i>","\n","ev","str","^Continue","/str","/ev",{"*":".^.c-0","flg":20},{"c-0":["^ ",{"->":"dialogue4"},"\n",{"#f":5}]}],{"#f":1}],"dialogue4":[["^Lyra: You're funny.","\n","^Syviis: I know","\n","ev","str","^Continue","/str","/ev",{"*":".^.c-0","flg":20},{"c-0":["^ ",{"->":"dialogue5"},"\n",{"#f":5}]}],{"#f":1}],"dialogue5":[["^Lyra: Retracting my statement.","\n","^Syviis: Lame. Let's go, come on.","\n","ev","str","^Leave","/str","/ev",{"*":".^.c-0","flg":20},{"c-0":["^ ","end","\n",{"#f":5}]}],{"#f":1}],"#f":1}],"listDefs":{}}